{
  "Xan Lee": {
    "details": {
      "MountainPiece": [
        {
          "id": "dervq2pcw",
          "points": 24,
          "reason": "1000 peça(s) entregue(s) (12 conjunto(s) válido(s))",
          "date": "2025-12-03T14:24:00.339Z"
        }
      ],
      "Services": [
        {
          "id": "1rg774dt1",
          "points": 1,
          "reason": "Poi",
          "date": "2025-12-03T14:24:22.326Z"
        },
        {
          "id": "qmf6s6zd8",
          "points": 1,
          "reason": "inqui",
          "date": "2025-12-03T14:24:35.382Z"
        },
        {
          "id": "2lxzjx258",
          "points": 1,
          "reason": "GT",
          "date": "2025-12-03T14:24:56.102Z"
        },
        {
          "id": "k1y31csqi",
          "points": 1,
          "reason": "Last GT",
          "date": "2025-12-03T14:25:04.031Z"
        }
      ]
    }
  }
}